call_flow/__init__.py
call_flow/tools/__init__.py
call_flow/tools/call_flow_tool.py
call_flow/tools/utils.py
call_flow/yamls/call_flow_tool.yaml
tests/__init__.py
tests/test_call_flow_tool.py
call_place_intelligenct_flow-0.0.2.dist-info/METADATA
call_place_intelligenct_flow-0.0.2.dist-info/WHEEL
call_place_intelligenct_flow-0.0.2.dist-info/entry_points.txt
call_place_intelligenct_flow-0.0.2.dist-info/top_level.txt
call_place_intelligenct_flow-0.0.2.dist-info/RECORD
